[
   {
      "x":69.1,
      "y":72.3,
      "name":"Mysterious Righteous Book"
   },
   {
      "x":42.3,
      "y":18,
      "name":"Wrathful Shield"
   },
   {
      "x":50.7,
      "y":75.8,
      "name":"Tombstone"
   },
   {
      "x":38.4,
      "y":54.8,
      "name":"Sticky Sabaton's"
   },
   {
      "x":35.8,
      "y":69.4,
      "name":"Skippy's Bone"
   },
   {
      "x":41.5,
      "y":75.6,
      "name":"Spiced Rum"
   },
   {
      "x":40.7,
      "y":52,
      "name":"Scarlet Blunderbuss"
   },
   {
      "x":43.6,
      "y":70.1,
      "name":"Andorhal Manual"
   },
   {
      "x":54.3,
      "y":80.5,
      "name":"Wraithbone Ring"
   },
   {
      "x":52,
      "y":81.8,
      "name":"Libram of Remembrance"
   },
   {
      "x":53.2,
      "y":66.4,
      "name":"Corrupted Flower"
   },
   {
      "x":68.9,
      "y":73.5,
      "name":"Harvester's Cane"
   },
   {
      "x":53,
      "y":55.5,
      "name":"Empty Sack"
   },
   {
      "x":48.9,
      "y":31.7,
      "name":"Garmet Supplies"
   },
   {
      "x":44.9,
      "y":33.8,
      "name":"Northridge Hatchet"
   },
   {
      "x":53.2,
      "y":37,
      "name":"Scarlet Knight Sword"
   },
   {
      "x":41.7,
      "y":14.8,
      "name":"Scarlet Cursed Band"
   },
   {
      "x":36,
      "y":56.2,
      "name":"Flayer's Helmet"
   },
   {
      "x":65.5,
      "y":73.8,
      "name":"Skeletal Club"
   },
   {
      "x":51.7,
      "y":44.3,
      "name":"Shimmering Scarlet Cane"
   },
   {
      "x":48.5,
      "y":69.8,
      "name":"Execution Axe"
   },
   {
      "x":46.3,
      "y":52.6,
      "name":"Phylactery Shard"
   },
   {
      "x":44.7,
      "y":13.3,
      "name":"Scarlet Shield"
   },
   {
      "x":46.4,
      "y":13.7,
      "name":"Brightflame Codex"
   },
   {
      "x":60.6,
      "y":72.1,
      "name":"Scourgestalker’s Girdle"
   },
   {
      "x":55,
      "y":23.8,
      "name":"Scarlet Supplies"
   },
   {
      "x":48.9,
      "y":78.6,
      "name":"Plague Mask"
   },
   {
      "x":39.6,
      "y":68.7,
      "name":"Abomination Hook"
   },
   {
      "x":54.9,
      "y":45.6,
      "name":"Charred Slicer"
   },
   {
      "x":59.6,
      "y":53.2,
      "name":"Graveyard Striker"
   },
   {
      "x":45.9,
      "y":62.3,
      "name":"Ebonblight Slippers"
   },
   {
      "x":48,
      "y":22.9,
      "name":"Sentinel Sharpshooter"
   },
   {
      "x":42.4,
      "y":18.7,
      "name":"Burning Judgement"
   },
   {
      "x":42.1,
      "y":59.6,
      "name":"Bonescourge Dagger"
   },
   {
      "x":69.7,
      "y":69.1,
      "name":"Gateway"
   },
   {
      "x":68,
      "y":61.4,
      "name":"Gateway"
   },
   {
      "x":68.1,
      "y":78.2,
      "name":"Prisoner's Equipment"
   },
   {
      "x":44.1,
      "y":98.3,
      "name":"Food Stores"
   },
   {
      "x":44,
      "y":98.4,
      "name":"Tanning Rack"
   },
   {
      "x":44.1,
      "y":98.3,
      "name":"Turtle Shell"
   },
   {
      "x":42.3,
      "y":18,
      "name":"Wrathful Shield"
   },
   {
      "x":85.6,
      "y":61.7,
      "name":"Mossflayer Corpse"
   },
   {
      "x":77.5,
      "y":58.7,
      "name":"Baby Plaguebat"
   },
   {
      "x":41.7,
      "y":14.8,
      "name":"Bandages Prop"
   },
   {
      "x":42.2,
      "y":14.6,
      "name":"Chained Skeleton Prop"
   },
   {
      "x":45.3,
      "y":44.6,
      "name":"Slightly-Damaged Chest"
   },
   {
      "x":80.5,
      "y":74.2,
      "name":"Apothecary Sack"
   },
   {
      "x":53,
      "y":55.5,
      "name":"Empty Sack"
   },
   {
      "x":48.9,
      "y":31.7,
      "name":"Garmet Supplies"
   },
   {
      "x":44.9,
      "y":33.8,
      "name":"Northridge Hatchet"
   },
   {
      "x":53.2,
      "y":37,
      "name":"Scarlet Knight Sword"
   },
   {
      "x":41.7,
      "y":14.8,
      "name":"Scarlet Band"
   },
   {
      "x":51.7,
      "y":44.3,
      "name":"Shimmering Scarlet Cane"
   },
   {
      "x":46.3,
      "y":52.6,
      "name":"Phylactery Shard"
   },
   {
      "x":44.7,
      "y":13.3,
      "name":"Scarlet Shield"
   },
   {
      "x":46.4,
      "y":13.7,
      "name":"Brightflame Codex"
   },
   {
      "x":55,
      "y":23.8,
      "name":"Scarlet Supplies"
   },
   {
      "x":54.9,
      "y":45.6,
      "name":"Charred Slicer"
   },
   {
      "x":59.8,
      "y":53.3,
      "name":"Graveyard Striker"
   },
   {
      "x":52.7,
      "y":19.3,
      "name":"Tracker's Plagued Spike"
   },
   {
      "x":48,
      "y":22.9,
      "name":"Sentinel Sharpshooter"
   },
   {
      "x":42.4,
      "y":18.7,
      "name":"Burning Judgement"
   },
   {
      "x":57.9,
      "y":36.2,
      "name":"Radley's Special Scope"
   },
   {
      "x":63.8,
      "y":57.1,
      "name":"Fetid Blade"
   },
   {
      "x":45.3,
      "y":15.5,
      "name":"Scarlet Chest"
   },
   {
      "x":41.7,
      "y":14.8,
      "name":"Scarlet Cursed Band"
   },
   {
      "x":55,
      "y":23.8,
      "name":"Scarlet Supplies"
   },
   {
      "x":69.4,
      "y":69.9,
      "name":"Scholomance Supplies"
   }
]
